INSTALL.txt
LICENSE.txt
README.txt
distribute_setup.py
setup.cfg
setup.py
ibidem/__init__.py
ibidem/django/__init__.py
ibidem/django/util.py
ibidem_django_util.egg-info/PKG-INFO
ibidem_django_util.egg-info/SOURCES.txt
ibidem_django_util.egg-info/dependency_links.txt
ibidem_django_util.egg-info/namespace_packages.txt
ibidem_django_util.egg-info/top_level.txt
ibidem_django_util.egg-info/zip-safe