Metadata-Version: 1.0
Name: ibidem-django-util
Version: 0.6.1
Summary: Ibidem Django utilities
Home-page: http://ibidem.homeip.net/Misc/wiki/Django/Utils
Author: Morten Lied Johansen
Author-email: mortenjo@ifi.uio.no
License: LGPL
Keywords: ibidem django util
Platform: UNKNOWN
Classifier: Development Status :: 4 - Beta
Classifier: Framework :: Django
Classifier: Intended Audience :: Developers
Classifier: License :: OSI Approved :: GNU Library or Lesser General Public License (LGPL)
Classifier: Operating System :: OS Independent
Classifier: Programming Language :: Python
Classifier: Topic :: Software Development :: Libraries :: Python Modules
